pytbucket/__init__.py
pytbucket/limiter/__init__.py
pytbucket/limiter/bucket.py
pytbucket/limiter/limit.py
pytbucket/limiter/limiter.py
pytbucket/limiter/memory.py
pytbucket/limiter/refiller.py
pytbucket/limiter/tmp_file.py
pytbucket/tests/__init__.py
pytbucket/tests/test_limiter.py
pytbucket-0.1.2.dist-info/METADATA
pytbucket-0.1.2.dist-info/WHEEL
pytbucket-0.1.2.dist-info/RECORD
